MANIFEST.in
Makefile
README.md
setup.py
docsource/broker.rst
docsource/client.rst
docsource/conf.py
docsource/index.rst
docsource/util.rst
docsource/worker.rst
mdp/__init__.py
mdp/broker.py
mdp/client.py
mdp/mybroker.py
mdp/myclient.py
mdp/myworker.py
mdp/test_client.py
mdp/test_worker.py
mdp/titanicworker.py
mdp/util.py
mdp/worker.py
pyzmq_mdp.egg-info/PKG-INFO
pyzmq_mdp.egg-info/SOURCES.txt
pyzmq_mdp.egg-info/dependency_links.txt
pyzmq_mdp.egg-info/not-zip-safe
pyzmq_mdp.egg-info/top_level.txt