Metadata-Version: 1.0
Name: pyzmq-mdp
Version: 0.2
Summary: ZeroMQ MDP protocol in Python using pyzmq
Home-page: https://github.com/guidog/pyzmq-mdp
Author: Guido Goldstein
Author-email: gst-py@a-nugget.de
License: UNKNOWN
Platform: UNKNOWN
